setup.py
odoo/addons/helpdesk_ticket_activity_ids/CHANGELOG.md
odoo/addons/helpdesk_ticket_activity_ids/README.rst
odoo/addons/helpdesk_ticket_activity_ids/__init__.py
odoo/addons/helpdesk_ticket_activity_ids/__manifest__.py
odoo/addons/helpdesk_ticket_activity_ids/i18n/ca_ES.po
odoo/addons/helpdesk_ticket_activity_ids/i18n/es.po
odoo/addons/helpdesk_ticket_activity_ids/models/__init__.py
odoo/addons/helpdesk_ticket_activity_ids/models/helpdesk_ticket.py
odoo/addons/helpdesk_ticket_activity_ids/models/mail_activity.py
odoo/addons/helpdesk_ticket_activity_ids/static/description/icon.png
odoo/addons/helpdesk_ticket_activity_ids/static/src/css/mail_activity_tree_view.css
odoo/addons/helpdesk_ticket_activity_ids/static/src/js/list_renderer.js
odoo/addons/helpdesk_ticket_activity_ids/tests/__init__.py
odoo/addons/helpdesk_ticket_activity_ids/tests/test_helpdesk_ticket.py
odoo/addons/helpdesk_ticket_activity_ids/views/helpdesk_ticket.xml
odoo/addons/helpdesk_ticket_activity_ids/views/mail_activity.xml
odoo_addon_helpdesk_ticket_activity_ids.egg-info/PKG-INFO
odoo_addon_helpdesk_ticket_activity_ids.egg-info/SOURCES.txt
odoo_addon_helpdesk_ticket_activity_ids.egg-info/dependency_links.txt
odoo_addon_helpdesk_ticket_activity_ids.egg-info/not-zip-safe
odoo_addon_helpdesk_ticket_activity_ids.egg-info/requires.txt
odoo_addon_helpdesk_ticket_activity_ids.egg-info/top_level.txt